semantic_deduplicator/__init__.py
semantic_deduplicator/main.py
semantic_deduplicator/utils.py
semantic_deduplicator-0.0.10.dist-info/METADATA
semantic_deduplicator-0.0.10.dist-info/WHEEL
semantic_deduplicator-0.0.10.dist-info/licenses/LICENSE
semantic_deduplicator-0.0.10.dist-info/RECORD
