Metadata-Version: 2.1
Name: semantic_deduplicator
Version: 0.0.10
Summary: A simple python package to deduplicate items based on their semantic meaning
Project-URL: Homepage, https://github.com/gkamradt/SemanticDeduplicator
Project-URL: Bug Tracker, https://github.com/gkamradt/SemanticDeduplicator/issues
Author-email: Greg Kamradt <contact@dataindependent.com>
License-File: LICENSE
Classifier: License :: OSI Approved :: MIT License
Classifier: Operating System :: OS Independent
Classifier: Programming Language :: Python :: 3
Requires-Python: >=3.9
Requires-Dist: numpy
Requires-Dist: openai
Requires-Dist: python-dotenv
